{
    "owner_org": "a9a8e392-9f69-493e-8b44-4a1586725a66", 
    "maintainer": "http://standaarden.overheid.nl/owms/terms/Rijkswaterstaat", 
    "relationships_as_object": [], 
    "lod_stars": "0", 
    "private": false, 
    "maintainer_email": "servicedesk-data@rws.nl", 
    "num_tags": 4, 
    "id": "470ff0f4-66ca-4960-ac23-4119d091c434", 
    "metadata_created": "2015-03-26T13:12:13.131839", 
    "metadata_modified": "2015-04-20T01:49:02.829403", 
    "author": null, 
    "author_email": null, 
    "isopen": true, 
    "state": "active", 
    "source": "ngr", 
    "theme": "http://standaarden.overheid.nl/owms/terms/Organisatie_en_beleid", 
    "version": null, 
    "maintainer_facet": "http://standaarden.overheid.nl/owms/terms/Rijkswaterstaat", 
    "md_soortwijziging": ":updated", 
    "spatial": "", 
    "license_id": "cc-0", 
    "contact_point": "ngr@test.com", 
    "type": "dataset", 
    "md_uri": "http://nationaalgeoregister.nl/geonetwork?uuid=730bc0c4-638d-4cd2-a44d-38b6e28ecff5", 
    "resources": [
        {
            "resource_group_id": "5ad039bb-bd27-461f-8a39-154a31d0422a", 
            "protocol": "OGC:WMS", 
            "cache_last_updated": null, 
            "revision_timestamp": "2015-04-20T01:49:02.828340", 
            "webstore_last_updated": null, 
            "id": "779c3a19-236f-4f61-8fd0-b8433c613227", 
            "size": null, 
            "state": "active", 
            "hash": "", 
            "description": "", 
            "format": "ogc:wms", 
            "tracking_summary": {
                "total": 0, 
                "recent": 0
            }, 
            "mimetype_inner": null, 
            "url_type": null, 
            "mimetype": null, 
            "cache_url": null, 
            "name": "j_lab_25_12", 
            "created": "2015-04-20T03:49:03.732927", 
            "url": "http://geoservices.rijkswaterstaat.nl/nis_kustlijnkaart", 
            "webstore_url": null, 
            "last_modified": null, 
            "position": 0, 
            "revision_id": "d5cbbaa4-d77c-4380-807f-783f6485c787", 
            "resource_type": null
        }, 
        {
            "resource_group_id": "5ad039bb-bd27-461f-8a39-154a31d0422a", 
            "protocol": "OGC:WFS", 
            "cache_last_updated": null, 
            "revision_timestamp": "2015-04-20T01:49:02.828340", 
            "webstore_last_updated": null, 
            "id": "820b5bcd-17e1-4f01-ab71-7b9f4dd1ec11", 
            "size": null, 
            "state": "active", 
            "hash": "", 
            "description": "", 
            "format": "ogc:wfs", 
            "tracking_summary": {
                "total": 0, 
                "recent": 0
            }, 
            "mimetype_inner": null, 
            "url_type": null, 
            "mimetype": null, 
            "cache_url": null, 
            "name": "j_lab_25_12", 
            "created": "2015-04-20T03:49:03.732952", 
            "url": "http://geoservices.rijkswaterstaat.nl/nis_kustlijnkaart", 
            "webstore_url": null, 
            "last_modified": null, 
            "position": 1, 
            "revision_id": "d5cbbaa4-d77c-4380-807f-783f6485c787", 
            "resource_type": null
        }, 
        {
            "resource_group_id": "5ad039bb-bd27-461f-8a39-154a31d0422a", 
            "protocol": "OGC:WMS", 
            "cache_last_updated": null, 
            "revision_timestamp": "2015-04-20T01:49:02.828340", 
            "webstore_last_updated": null, 
            "id": "2a0139d8-3c2b-4193-800b-52151a9e5976", 
            "size": null, 
            "state": "active", 
            "hash": "", 
            "description": "", 
            "format": "ogc:wms", 
            "tracking_summary": {
                "total": 0, 
                "recent": 0
            }, 
            "mimetype_inner": null, 
            "url_type": null, 
            "mimetype": null, 
            "cache_url": null, 
            "name": "j_lab_50_12", 
            "created": "2015-04-20T03:49:03.732960", 
            "url": "http://geoservices.rijkswaterstaat.nl/nis_kustlijnkaart", 
            "webstore_url": null, 
            "last_modified": null, 
            "position": 2, 
            "revision_id": "d5cbbaa4-d77c-4380-807f-783f6485c787", 
            "resource_type": null
        }, 
        {
            "resource_group_id": "5ad039bb-bd27-461f-8a39-154a31d0422a", 
            "protocol": "OGC:WFS", 
            "cache_last_updated": null, 
            "revision_timestamp": "2015-04-20T01:49:02.828340", 
            "webstore_last_updated": null, 
            "id": "83cee7cb-bd59-4402-8bda-ef7af3e4108a", 
            "size": null, 
            "state": "active", 
            "hash": "", 
            "description": "", 
            "format": "ogc:wfs", 
            "tracking_summary": {
                "total": 0, 
                "recent": 0
            }, 
            "mimetype_inner": null, 
            "url_type": null, 
            "mimetype": null, 
            "cache_url": null, 
            "name": "j_lab_50_12", 
            "created": "2015-04-20T03:49:03.732966", 
            "url": "http://geoservices.rijkswaterstaat.nl/nis_kustlijnkaart", 
            "webstore_url": null, 
            "last_modified": null, 
            "position": 3, 
            "revision_id": "d5cbbaa4-d77c-4380-807f-783f6485c787", 
            "resource_type": null
        }, 
        {
            "resource_group_id": "5ad039bb-bd27-461f-8a39-154a31d0422a", 
            "protocol": "OGC:WMS", 
            "cache_last_updated": null, 
            "revision_timestamp": "2015-04-20T01:49:02.828340", 
            "webstore_last_updated": null, 
            "id": "326cde85-cc59-43c0-9768-c00930176d3a", 
            "size": null, 
            "state": "active", 
            "hash": "", 
            "description": "", 
            "format": "ogc:wms", 
            "tracking_summary": {
                "total": 0, 
                "recent": 0
            }, 
            "mimetype_inner": null, 
            "url_type": null, 
            "mimetype": null, 
            "cache_url": null, 
            "name": "j_lab_100_12", 
            "created": "2015-04-20T03:49:03.732973", 
            "url": "http://geoservices.rijkswaterstaat.nl/nis_kustlijnkaart", 
            "webstore_url": null, 
            "last_modified": null, 
            "position": 4, 
            "revision_id": "d5cbbaa4-d77c-4380-807f-783f6485c787", 
            "resource_type": null
        }, 
        {
            "resource_group_id": "5ad039bb-bd27-461f-8a39-154a31d0422a", 
            "protocol": "OGC:WFS", 
            "cache_last_updated": null, 
            "revision_timestamp": "2015-04-20T01:49:02.828340", 
            "webstore_last_updated": null, 
            "id": "dabf3848-d7e7-4901-bf4b-e6423d5f50d6", 
            "size": null, 
            "state": "active", 
            "hash": "", 
            "description": "", 
            "format": "ogc:wfs", 
            "tracking_summary": {
                "total": 0, 
                "recent": 0
            }, 
            "mimetype_inner": null, 
            "url_type": null, 
            "mimetype": null, 
            "cache_url": null, 
            "name": "j_lab_100_12", 
            "created": "2015-04-20T03:49:03.732979", 
            "url": "http://geoservices.rijkswaterstaat.nl/nis_kustlijnkaart", 
            "webstore_url": null, 
            "last_modified": null, 
            "position": 5, 
            "revision_id": "d5cbbaa4-d77c-4380-807f-783f6485c787", 
            "resource_type": null
        }, 
        {
            "resource_group_id": "5ad039bb-bd27-461f-8a39-154a31d0422a", 
            "protocol": "OGC:WMS", 
            "cache_last_updated": null, 
            "revision_timestamp": "2015-04-20T01:49:02.828340", 
            "webstore_last_updated": null, 
            "id": "51dee845-301b-4021-b62c-8607b3c5a70e", 
            "size": null, 
            "state": "active", 
            "hash": "", 
            "description": "", 
            "format": "ogc:wms", 
            "tracking_summary": {
                "total": 0, 
                "recent": 0
            }, 
            "mimetype_inner": null, 
            "url_type": null, 
            "mimetype": null, 
            "cache_url": null, 
            "name": "j_raai_12", 
            "created": "2015-04-20T03:49:03.732985", 
            "url": "http://geoservices.rijkswaterstaat.nl/nis_kustlijnkaart", 
            "webstore_url": null, 
            "last_modified": null, 
            "position": 6, 
            "revision_id": "d5cbbaa4-d77c-4380-807f-783f6485c787", 
            "resource_type": null
        }, 
        {
            "resource_group_id": "5ad039bb-bd27-461f-8a39-154a31d0422a", 
            "protocol": "OGC:WFS", 
            "cache_last_updated": null, 
            "revision_timestamp": "2015-04-20T01:49:02.828340", 
            "webstore_last_updated": null, 
            "id": "cc342147-c455-40f6-b207-bd7ef6ea28f2", 
            "size": null, 
            "state": "active", 
            "hash": "", 
            "description": "", 
            "format": "ogc:wfs", 
            "tracking_summary": {
                "total": 0, 
                "recent": 0
            }, 
            "mimetype_inner": null, 
            "url_type": null, 
            "mimetype": null, 
            "cache_url": null, 
            "name": "j_raai_12", 
            "created": "2015-04-20T03:49:03.732991", 
            "url": "http://geoservices.rijkswaterstaat.nl/nis_kustlijnkaart", 
            "webstore_url": null, 
            "last_modified": null, 
            "position": 7, 
            "revision_id": "d5cbbaa4-d77c-4380-807f-783f6485c787", 
            "resource_type": null
        }, 
        {
            "resource_group_id": "5ad039bb-bd27-461f-8a39-154a31d0422a", 
            "protocol": "OGC:WMS", 
            "cache_last_updated": null, 
            "revision_timestamp": "2015-04-20T01:49:02.828340", 
            "webstore_last_updated": null, 
            "id": "2257c384-ed80-4d81-ba48-862f3a484666", 
            "size": null, 
            "state": "active", 
            "hash": "", 
            "description": "", 
            "format": "ogc:wms", 
            "tracking_summary": {
                "total": 0, 
                "recent": 0
            }, 
            "mimetype_inner": null, 
            "url_type": null, 
            "mimetype": null, 
            "cache_url": null, 
            "name": "j_lab_25_11", 
            "created": "2015-04-20T03:49:03.732998", 
            "url": "http://geoservices.rijkswaterstaat.nl/nis_kustlijnkaart", 
            "webstore_url": null, 
            "last_modified": null, 
            "position": 8, 
            "revision_id": "d5cbbaa4-d77c-4380-807f-783f6485c787", 
            "resource_type": null
        }, 
        {
            "resource_group_id": "5ad039bb-bd27-461f-8a39-154a31d0422a", 
            "protocol": "OGC:WFS", 
            "cache_last_updated": null, 
            "revision_timestamp": "2015-04-20T01:49:02.828340", 
            "webstore_last_updated": null, 
            "id": "b00b8954-03dc-4339-9421-8d95c1637c2b", 
            "size": null, 
            "state": "active", 
            "hash": "", 
            "description": "", 
            "format": "ogc:wfs", 
            "tracking_summary": {
                "total": 0, 
                "recent": 0
            }, 
            "mimetype_inner": null, 
            "url_type": null, 
            "mimetype": null, 
            "cache_url": null, 
            "name": "j_lab_25_11", 
            "created": "2015-04-20T03:49:03.733004", 
            "url": "http://geoservices.rijkswaterstaat.nl/nis_kustlijnkaart", 
            "webstore_url": null, 
            "last_modified": null, 
            "position": 9, 
            "revision_id": "d5cbbaa4-d77c-4380-807f-783f6485c787", 
            "resource_type": null
        }, 
        {
            "resource_group_id": "5ad039bb-bd27-461f-8a39-154a31d0422a", 
            "protocol": "OGC:WMS", 
            "cache_last_updated": null, 
            "revision_timestamp": "2015-04-20T01:49:02.828340", 
            "webstore_last_updated": null, 
            "id": "a6673716-2c74-414c-912d-dd0b49a18b9d", 
            "size": null, 
            "state": "active", 
            "hash": "", 
            "description": "", 
            "format": "ogc:wms", 
            "tracking_summary": {
                "total": 0, 
                "recent": 0
            }, 
            "mimetype_inner": null, 
            "url_type": null, 
            "mimetype": null, 
            "cache_url": null, 
            "name": "j_lab_50_11", 
            "created": "2015-04-20T03:49:03.733010", 
            "url": "http://geoservices.rijkswaterstaat.nl/nis_kustlijnkaart", 
            "webstore_url": null, 
            "last_modified": null, 
            "position": 10, 
            "revision_id": "d5cbbaa4-d77c-4380-807f-783f6485c787", 
            "resource_type": null
        }, 
        {
            "resource_group_id": "5ad039bb-bd27-461f-8a39-154a31d0422a", 
            "protocol": "OGC:WFS", 
            "cache_last_updated": null, 
            "revision_timestamp": "2015-04-20T01:49:02.828340", 
            "webstore_last_updated": null, 
            "id": "af55b7b7-e785-49c5-90d7-b0c4c59cfcb2", 
            "size": null, 
            "state": "active", 
            "hash": "", 
            "description": "", 
            "format": "ogc:wfs", 
            "tracking_summary": {
                "total": 0, 
                "recent": 0
            }, 
            "mimetype_inner": null, 
            "url_type": null, 
            "mimetype": null, 
            "cache_url": null, 
            "name": "j_lab_50_11", 
            "created": "2015-04-20T03:49:03.733017", 
            "url": "http://geoservices.rijkswaterstaat.nl/nis_kustlijnkaart", 
            "webstore_url": null, 
            "last_modified": null, 
            "position": 11, 
            "revision_id": "d5cbbaa4-d77c-4380-807f-783f6485c787", 
            "resource_type": null
        }, 
        {
            "resource_group_id": "5ad039bb-bd27-461f-8a39-154a31d0422a", 
            "protocol": "OGC:WMS", 
            "cache_last_updated": null, 
            "revision_timestamp": "2015-04-20T01:49:02.828340", 
            "webstore_last_updated": null, 
            "id": "f9161eb0-1dd4-4ff5-bd4c-9fe2afd837fd", 
            "size": null, 
            "state": "active", 
            "hash": "", 
            "description": "", 
            "format": "ogc:wms", 
            "tracking_summary": {
                "total": 0, 
                "recent": 0
            }, 
            "mimetype_inner": null, 
            "url_type": null, 
            "mimetype": null, 
            "cache_url": null, 
            "name": "j_lab_100_11", 
            "created": "2015-04-20T03:49:03.733023", 
            "url": "http://geoservices.rijkswaterstaat.nl/nis_kustlijnkaart", 
            "webstore_url": null, 
            "last_modified": null, 
            "position": 12, 
            "revision_id": "d5cbbaa4-d77c-4380-807f-783f6485c787", 
            "resource_type": null
        }, 
        {
            "resource_group_id": "5ad039bb-bd27-461f-8a39-154a31d0422a", 
            "protocol": "OGC:WFS", 
            "cache_last_updated": null, 
            "revision_timestamp": "2015-04-20T01:49:02.828340", 
            "webstore_last_updated": null, 
            "id": "01a1083f-98be-4f1d-842c-30e7a5961971", 
            "size": null, 
            "state": "active", 
            "hash": "", 
            "description": "", 
            "format": "ogc:wfs", 
            "tracking_summary": {
                "total": 0, 
                "recent": 0
            }, 
            "mimetype_inner": null, 
            "url_type": null, 
            "mimetype": null, 
            "cache_url": null, 
            "name": "j_lab_100_11", 
            "created": "2015-04-20T03:49:03.733029", 
            "url": "http://geoservices.rijkswaterstaat.nl/nis_kustlijnkaart", 
            "webstore_url": null, 
            "last_modified": null, 
            "position": 13, 
            "revision_id": "d5cbbaa4-d77c-4380-807f-783f6485c787", 
            "resource_type": null
        }, 
        {
            "resource_group_id": "5ad039bb-bd27-461f-8a39-154a31d0422a", 
            "protocol": "OGC:WMS", 
            "cache_last_updated": null, 
            "revision_timestamp": "2015-04-20T01:49:02.828340", 
            "webstore_last_updated": null, 
            "id": "913eab3d-d6f5-489c-9058-f7438e761cd8", 
            "size": null, 
            "state": "active", 
            "hash": "", 
            "description": "", 
            "format": "ogc:wms", 
            "tracking_summary": {
                "total": 0, 
                "recent": 0
            }, 
            "mimetype_inner": null, 
            "url_type": null, 
            "mimetype": null, 
            "cache_url": null, 
            "name": "j_raai_11", 
            "created": "2015-04-20T03:49:03.733035", 
            "url": "http://geoservices.rijkswaterstaat.nl/nis_kustlijnkaart", 
            "webstore_url": null, 
            "last_modified": null, 
            "position": 14, 
            "revision_id": "d5cbbaa4-d77c-4380-807f-783f6485c787", 
            "resource_type": null
        }, 
        {
            "resource_group_id": "5ad039bb-bd27-461f-8a39-154a31d0422a", 
            "protocol": "OGC:WFS", 
            "cache_last_updated": null, 
            "revision_timestamp": "2015-04-20T01:49:02.828340", 
            "webstore_last_updated": null, 
            "id": "2bedda39-77fc-4a63-a7b4-21e70469ba2e", 
            "size": null, 
            "state": "active", 
            "hash": "", 
            "description": "", 
            "format": "ogc:wfs", 
            "tracking_summary": {
                "total": 0, 
                "recent": 0
            }, 
            "mimetype_inner": null, 
            "url_type": null, 
            "mimetype": null, 
            "cache_url": null, 
            "name": "j_raai_11", 
            "created": "2015-04-20T03:49:03.733042", 
            "url": "http://geoservices.rijkswaterstaat.nl/nis_kustlijnkaart", 
            "webstore_url": null, 
            "last_modified": null, 
            "position": 15, 
            "revision_id": "d5cbbaa4-d77c-4380-807f-783f6485c787", 
            "resource_type": null
        }, 
        {
            "resource_group_id": "5ad039bb-bd27-461f-8a39-154a31d0422a", 
            "protocol": "OGC:WMS", 
            "cache_last_updated": null, 
            "revision_timestamp": "2015-04-20T01:49:02.828340", 
            "webstore_last_updated": null, 
            "id": "ee85337d-3085-43f9-b15e-0e42bc072b79", 
            "size": null, 
            "state": "active", 
            "hash": "", 
            "description": "", 
            "format": "ogc:wms", 
            "tracking_summary": {
                "total": 0, 
                "recent": 0
            }, 
            "mimetype_inner": null, 
            "url_type": null, 
            "mimetype": null, 
            "cache_url": null, 
            "name": "j_lab_25_10", 
            "created": "2015-04-20T03:49:03.733048", 
            "url": "http://geoservices.rijkswaterstaat.nl/nis_kustlijnkaart", 
            "webstore_url": null, 
            "last_modified": null, 
            "position": 16, 
            "revision_id": "d5cbbaa4-d77c-4380-807f-783f6485c787", 
            "resource_type": null
        }, 
        {
            "resource_group_id": "5ad039bb-bd27-461f-8a39-154a31d0422a", 
            "protocol": "OGC:WFS", 
            "cache_last_updated": null, 
            "revision_timestamp": "2015-04-20T01:49:02.828340", 
            "webstore_last_updated": null, 
            "id": "583b36dc-696b-40c1-aa76-0533018f17c6", 
            "size": null, 
            "state": "active", 
            "hash": "", 
            "description": "", 
            "format": "ogc:wfs", 
            "tracking_summary": {
                "total": 0, 
                "recent": 0
            }, 
            "mimetype_inner": null, 
            "url_type": null, 
            "mimetype": null, 
            "cache_url": null, 
            "name": "j_lab_25_10", 
            "created": "2015-04-20T03:49:03.733054", 
            "url": "http://geoservices.rijkswaterstaat.nl/nis_kustlijnkaart", 
            "webstore_url": null, 
            "last_modified": null, 
            "position": 17, 
            "revision_id": "d5cbbaa4-d77c-4380-807f-783f6485c787", 
            "resource_type": null
        }, 
        {
            "resource_group_id": "5ad039bb-bd27-461f-8a39-154a31d0422a", 
            "protocol": "OGC:WMS", 
            "cache_last_updated": null, 
            "revision_timestamp": "2015-04-20T01:49:02.828340", 
            "webstore_last_updated": null, 
            "id": "847dff77-b365-4ebb-8a8f-270dab2738d6", 
            "size": null, 
            "state": "active", 
            "hash": "", 
            "description": "", 
            "format": "ogc:wms", 
            "tracking_summary": {
                "total": 0, 
                "recent": 0
            }, 
            "mimetype_inner": null, 
            "url_type": null, 
            "mimetype": null, 
            "cache_url": null, 
            "name": "j_lab_50_10", 
            "created": "2015-04-20T03:49:03.733061", 
            "url": "http://geoservices.rijkswaterstaat.nl/nis_kustlijnkaart", 
            "webstore_url": null, 
            "last_modified": null, 
            "position": 18, 
            "revision_id": "d5cbbaa4-d77c-4380-807f-783f6485c787", 
            "resource_type": null
        }, 
        {
            "resource_group_id": "5ad039bb-bd27-461f-8a39-154a31d0422a", 
            "protocol": "OGC:WFS", 
            "cache_last_updated": null, 
            "revision_timestamp": "2015-04-20T01:49:02.828340", 
            "webstore_last_updated": null, 
            "id": "c7a65738-b6d9-417c-b6f5-b246763fe072", 
            "size": null, 
            "state": "active", 
            "hash": "", 
            "description": "", 
            "format": "ogc:wfs", 
            "tracking_summary": {
                "total": 0, 
                "recent": 0
            }, 
            "mimetype_inner": null, 
            "url_type": null, 
            "mimetype": null, 
            "cache_url": null, 
            "name": "j_lab_50_10", 
            "created": "2015-04-20T03:49:03.733067", 
            "url": "http://geoservices.rijkswaterstaat.nl/nis_kustlijnkaart", 
            "webstore_url": null, 
            "last_modified": null, 
            "position": 19, 
            "revision_id": "d5cbbaa4-d77c-4380-807f-783f6485c787", 
            "resource_type": null
        }, 
        {
            "resource_group_id": "5ad039bb-bd27-461f-8a39-154a31d0422a", 
            "protocol": "OGC:WMS", 
            "cache_last_updated": null, 
            "revision_timestamp": "2015-04-20T01:49:02.828340", 
            "webstore_last_updated": null, 
            "id": "53ca7a4a-4bad-413c-a62e-2daa4c83d36b", 
            "size": null, 
            "state": "active", 
            "hash": "", 
            "description": "", 
            "format": "ogc:wms", 
            "tracking_summary": {
                "total": 0, 
                "recent": 0
            }, 
            "mimetype_inner": null, 
            "url_type": null, 
            "mimetype": null, 
            "cache_url": null, 
            "name": "j_lab_100_10", 
            "created": "2015-04-20T03:49:03.733073", 
            "url": "http://geoservices.rijkswaterstaat.nl/nis_kustlijnkaart", 
            "webstore_url": null, 
            "last_modified": null, 
            "position": 20, 
            "revision_id": "d5cbbaa4-d77c-4380-807f-783f6485c787", 
            "resource_type": null
        }, 
        {
            "resource_group_id": "5ad039bb-bd27-461f-8a39-154a31d0422a", 
            "protocol": "OGC:WFS", 
            "cache_last_updated": null, 
            "revision_timestamp": "2015-04-20T01:49:02.828340", 
            "webstore_last_updated": null, 
            "id": "28fd9798-0d9e-4ecb-82c8-33c945a6c5ff", 
            "size": null, 
            "state": "active", 
            "hash": "", 
            "description": "", 
            "format": "ogc:wfs", 
            "tracking_summary": {
                "total": 0, 
                "recent": 0
            }, 
            "mimetype_inner": null, 
            "url_type": null, 
            "mimetype": null, 
            "cache_url": null, 
            "name": "j_lab_100_10", 
            "created": "2015-04-20T03:49:03.733080", 
            "url": "http://geoservices.rijkswaterstaat.nl/nis_kustlijnkaart", 
            "webstore_url": null, 
            "last_modified": null, 
            "position": 21, 
            "revision_id": "d5cbbaa4-d77c-4380-807f-783f6485c787", 
            "resource_type": null
        }, 
        {
            "resource_group_id": "5ad039bb-bd27-461f-8a39-154a31d0422a", 
            "protocol": "OGC:WMS", 
            "cache_last_updated": null, 
            "revision_timestamp": "2015-04-20T01:49:02.828340", 
            "webstore_last_updated": null, 
            "id": "4fb174ff-ab4f-46e2-88c9-7d0d67be95c4", 
            "size": null, 
            "state": "active", 
            "hash": "", 
            "description": "", 
            "format": "ogc:wms", 
            "tracking_summary": {
                "total": 0, 
                "recent": 0
            }, 
            "mimetype_inner": null, 
            "url_type": null, 
            "mimetype": null, 
            "cache_url": null, 
            "name": "j_raai_10", 
            "created": "2015-04-20T03:49:03.733086", 
            "url": "http://geoservices.rijkswaterstaat.nl/nis_kustlijnkaart", 
            "webstore_url": null, 
            "last_modified": null, 
            "position": 22, 
            "revision_id": "d5cbbaa4-d77c-4380-807f-783f6485c787", 
            "resource_type": null
        }, 
        {
            "resource_group_id": "5ad039bb-bd27-461f-8a39-154a31d0422a", 
            "protocol": "OGC:WFS", 
            "cache_last_updated": null, 
            "revision_timestamp": "2015-04-20T01:49:02.828340", 
            "webstore_last_updated": null, 
            "id": "c09842e0-b3b7-4d00-b4ef-c34b2583fd8c", 
            "size": null, 
            "state": "active", 
            "hash": "", 
            "description": "", 
            "format": "ogc:wfs", 
            "tracking_summary": {
                "total": 0, 
                "recent": 0
            }, 
            "mimetype_inner": null, 
            "url_type": null, 
            "mimetype": null, 
            "cache_url": null, 
            "name": "j_raai_10", 
            "created": "2015-04-20T03:49:03.733092", 
            "url": "http://geoservices.rijkswaterstaat.nl/nis_kustlijnkaart", 
            "webstore_url": null, 
            "last_modified": null, 
            "position": 23, 
            "revision_id": "d5cbbaa4-d77c-4380-807f-783f6485c787", 
            "resource_type": null
        }, 
        {
            "resource_group_id": "5ad039bb-bd27-461f-8a39-154a31d0422a", 
            "protocol": "OGC:WMS", 
            "cache_last_updated": null, 
            "revision_timestamp": "2015-04-20T01:49:02.828340", 
            "webstore_last_updated": null, 
            "id": "cb1d9b6a-10a5-4c33-8617-282e9ffcc2b3", 
            "size": null, 
            "state": "active", 
            "hash": "", 
            "description": "", 
            "format": "ogc:wms", 
            "tracking_summary": {
                "total": 0, 
                "recent": 0
            }, 
            "mimetype_inner": null, 
            "url_type": null, 
            "mimetype": null, 
            "cache_url": null, 
            "name": "j_lab_25_09", 
            "created": "2015-04-20T03:49:03.733099", 
            "url": "http://geoservices.rijkswaterstaat.nl/nis_kustlijnkaart", 
            "webstore_url": null, 
            "last_modified": null, 
            "position": 24, 
            "revision_id": "d5cbbaa4-d77c-4380-807f-783f6485c787", 
            "resource_type": null
        }, 
        {
            "resource_group_id": "5ad039bb-bd27-461f-8a39-154a31d0422a", 
            "protocol": "OGC:WFS", 
            "cache_last_updated": null, 
            "revision_timestamp": "2015-04-20T01:49:02.828340", 
            "webstore_last_updated": null, 
            "id": "545addd3-a94d-4922-af90-8e193c1aad16", 
            "size": null, 
            "state": "active", 
            "hash": "", 
            "description": "", 
            "format": "ogc:wfs", 
            "tracking_summary": {
                "total": 0, 
                "recent": 0
            }, 
            "mimetype_inner": null, 
            "url_type": null, 
            "mimetype": null, 
            "cache_url": null, 
            "name": "j_lab_25_09", 
            "created": "2015-04-20T03:49:03.733105", 
            "url": "http://geoservices.rijkswaterstaat.nl/nis_kustlijnkaart", 
            "webstore_url": null, 
            "last_modified": null, 
            "position": 25, 
            "revision_id": "d5cbbaa4-d77c-4380-807f-783f6485c787", 
            "resource_type": null
        }, 
        {
            "resource_group_id": "5ad039bb-bd27-461f-8a39-154a31d0422a", 
            "protocol": "OGC:WMS", 
            "cache_last_updated": null, 
            "revision_timestamp": "2015-04-20T01:49:02.828340", 
            "webstore_last_updated": null, 
            "id": "0dbce136-da61-44ae-86c0-606c38221570", 
            "size": null, 
            "state": "active", 
            "hash": "", 
            "description": "", 
            "format": "ogc:wms", 
            "tracking_summary": {
                "total": 0, 
                "recent": 0
            }, 
            "mimetype_inner": null, 
            "url_type": null, 
            "mimetype": null, 
            "cache_url": null, 
            "name": "j_lab_50_09", 
            "created": "2015-04-20T03:49:03.733111", 
            "url": "http://geoservices.rijkswaterstaat.nl/nis_kustlijnkaart", 
            "webstore_url": null, 
            "last_modified": null, 
            "position": 26, 
            "revision_id": "d5cbbaa4-d77c-4380-807f-783f6485c787", 
            "resource_type": null
        }, 
        {
            "resource_group_id": "5ad039bb-bd27-461f-8a39-154a31d0422a", 
            "protocol": "OGC:WFS", 
            "cache_last_updated": null, 
            "revision_timestamp": "2015-04-20T01:49:02.828340", 
            "webstore_last_updated": null, 
            "id": "d3d5a768-f489-4e7d-a4f9-d0861e551e23", 
            "size": null, 
            "state": "active", 
            "hash": "", 
            "description": "", 
            "format": "ogc:wfs", 
            "tracking_summary": {
                "total": 0, 
                "recent": 0
            }, 
            "mimetype_inner": null, 
            "url_type": null, 
            "mimetype": null, 
            "cache_url": null, 
            "name": "j_lab_50_09", 
            "created": "2015-04-20T03:49:03.733117", 
            "url": "http://geoservices.rijkswaterstaat.nl/nis_kustlijnkaart", 
            "webstore_url": null, 
            "last_modified": null, 
            "position": 27, 
            "revision_id": "d5cbbaa4-d77c-4380-807f-783f6485c787", 
            "resource_type": null
        }, 
        {
            "resource_group_id": "5ad039bb-bd27-461f-8a39-154a31d0422a", 
            "protocol": "OGC:WMS", 
            "cache_last_updated": null, 
            "revision_timestamp": "2015-04-20T01:49:02.828340", 
            "webstore_last_updated": null, 
            "id": "90e4c008-5053-4a51-9f0e-27e3b6ba2c5a", 
            "size": null, 
            "state": "active", 
            "hash": "", 
            "description": "", 
            "format": "ogc:wms", 
            "tracking_summary": {
                "total": 0, 
                "recent": 0
            }, 
            "mimetype_inner": null, 
            "url_type": null, 
            "mimetype": null, 
            "cache_url": null, 
            "name": "j_lab_100_09", 
            "created": "2015-04-20T03:49:03.733124", 
            "url": "http://geoservices.rijkswaterstaat.nl/nis_kustlijnkaart", 
            "webstore_url": null, 
            "last_modified": null, 
            "position": 28, 
            "revision_id": "d5cbbaa4-d77c-4380-807f-783f6485c787", 
            "resource_type": null
        }, 
        {
            "resource_group_id": "5ad039bb-bd27-461f-8a39-154a31d0422a", 
            "protocol": "OGC:WFS", 
            "cache_last_updated": null, 
            "revision_timestamp": "2015-04-20T01:49:02.828340", 
            "webstore_last_updated": null, 
            "id": "9a1603c1-ab8c-4fb5-9fd9-17abe50c2082", 
            "size": null, 
            "state": "active", 
            "hash": "", 
            "description": "", 
            "format": "ogc:wfs", 
            "tracking_summary": {
                "total": 0, 
                "recent": 0
            }, 
            "mimetype_inner": null, 
            "url_type": null, 
            "mimetype": null, 
            "cache_url": null, 
            "name": "j_lab_100_09", 
            "created": "2015-04-20T03:49:03.733130", 
            "url": "http://geoservices.rijkswaterstaat.nl/nis_kustlijnkaart", 
            "webstore_url": null, 
            "last_modified": null, 
            "position": 29, 
            "revision_id": "d5cbbaa4-d77c-4380-807f-783f6485c787", 
            "resource_type": null
        }, 
        {
            "resource_group_id": "5ad039bb-bd27-461f-8a39-154a31d0422a", 
            "protocol": "OGC:WMS", 
            "cache_last_updated": null, 
            "revision_timestamp": "2015-04-20T01:49:02.828340", 
            "webstore_last_updated": null, 
            "id": "60d3ada6-f289-4352-97cc-4e65e3a80355", 
            "size": null, 
            "state": "active", 
            "hash": "", 
            "description": "", 
            "format": "ogc:wms", 
            "tracking_summary": {
                "total": 0, 
                "recent": 0
            }, 
            "mimetype_inner": null, 
            "url_type": null, 
            "mimetype": null, 
            "cache_url": null, 
            "name": "j_raai_09", 
            "created": "2015-04-20T03:49:03.733136", 
            "url": "http://geoservices.rijkswaterstaat.nl/nis_kustlijnkaart", 
            "webstore_url": null, 
            "last_modified": null, 
            "position": 30, 
            "revision_id": "d5cbbaa4-d77c-4380-807f-783f6485c787", 
            "resource_type": null
        }, 
        {
            "resource_group_id": "5ad039bb-bd27-461f-8a39-154a31d0422a", 
            "protocol": "OGC:WFS", 
            "cache_last_updated": null, 
            "revision_timestamp": "2015-04-20T01:49:02.828340", 
            "webstore_last_updated": null, 
            "id": "88921bf2-9688-4fdc-baa1-9ba0831a0e95", 
            "size": null, 
            "state": "active", 
            "hash": "", 
            "description": "", 
            "format": "ogc:wfs", 
            "tracking_summary": {
                "total": 0, 
                "recent": 0
            }, 
            "mimetype_inner": null, 
            "url_type": null, 
            "mimetype": null, 
            "cache_url": null, 
            "name": "j_raai_09", 
            "created": "2015-04-20T03:49:03.733142", 
            "url": "http://geoservices.rijkswaterstaat.nl/nis_kustlijnkaart", 
            "webstore_url": null, 
            "last_modified": null, 
            "position": 31, 
            "revision_id": "d5cbbaa4-d77c-4380-807f-783f6485c787", 
            "resource_type": null
        }, 
        {
            "resource_group_id": "5ad039bb-bd27-461f-8a39-154a31d0422a", 
            "protocol": "OGC:WMS", 
            "cache_last_updated": null, 
            "revision_timestamp": "2015-04-20T01:49:02.828340", 
            "webstore_last_updated": null, 
            "id": "dbda4874-8674-47e1-afcb-237388f1295e", 
            "size": null, 
            "state": "active", 
            "hash": "", 
            "description": "", 
            "format": "ogc:wms", 
            "tracking_summary": {
                "total": 0, 
                "recent": 0
            }, 
            "mimetype_inner": null, 
            "url_type": null, 
            "mimetype": null, 
            "cache_url": null, 
            "name": "j_lab_25_08", 
            "created": "2015-04-20T03:49:03.733148", 
            "url": "http://geoservices.rijkswaterstaat.nl/nis_kustlijnkaart", 
            "webstore_url": null, 
            "last_modified": null, 
            "position": 32, 
            "revision_id": "d5cbbaa4-d77c-4380-807f-783f6485c787", 
            "resource_type": null
        }, 
        {
            "resource_group_id": "5ad039bb-bd27-461f-8a39-154a31d0422a", 
            "protocol": "OGC:WFS", 
            "cache_last_updated": null, 
            "revision_timestamp": "2015-04-20T01:49:02.828340", 
            "webstore_last_updated": null, 
            "id": "224a055d-5037-407f-af64-7db517ffa0ce", 
            "size": null, 
            "state": "active", 
            "hash": "", 
            "description": "", 
            "format": "ogc:wfs", 
            "tracking_summary": {
                "total": 0, 
                "recent": 0
            }, 
            "mimetype_inner": null, 
            "url_type": null, 
            "mimetype": null, 
            "cache_url": null, 
            "name": "j_lab_25_08", 
            "created": "2015-04-20T03:49:03.733155", 
            "url": "http://geoservices.rijkswaterstaat.nl/nis_kustlijnkaart", 
            "webstore_url": null, 
            "last_modified": null, 
            "position": 33, 
            "revision_id": "d5cbbaa4-d77c-4380-807f-783f6485c787", 
            "resource_type": null
        }, 
        {
            "resource_group_id": "5ad039bb-bd27-461f-8a39-154a31d0422a", 
            "protocol": "OGC:WMS", 
            "cache_last_updated": null, 
            "revision_timestamp": "2015-04-20T01:49:02.828340", 
            "webstore_last_updated": null, 
            "id": "8077e87c-cc1d-4300-8864-45232daac1d2", 
            "size": null, 
            "state": "active", 
            "hash": "", 
            "description": "", 
            "format": "ogc:wms", 
            "tracking_summary": {
                "total": 0, 
                "recent": 0
            }, 
            "mimetype_inner": null, 
            "url_type": null, 
            "mimetype": null, 
            "cache_url": null, 
            "name": "j_lab_50_08", 
            "created": "2015-04-20T03:49:03.733161", 
            "url": "http://geoservices.rijkswaterstaat.nl/nis_kustlijnkaart", 
            "webstore_url": null, 
            "last_modified": null, 
            "position": 34, 
            "revision_id": "d5cbbaa4-d77c-4380-807f-783f6485c787", 
            "resource_type": null
        }, 
        {
            "resource_group_id": "5ad039bb-bd27-461f-8a39-154a31d0422a", 
            "protocol": "OGC:WFS", 
            "cache_last_updated": null, 
            "revision_timestamp": "2015-04-20T01:49:02.828340", 
            "webstore_last_updated": null, 
            "id": "31d3dd75-b266-4b79-9920-020efa1f8f6e", 
            "size": null, 
            "state": "active", 
            "hash": "", 
            "description": "", 
            "format": "ogc:wfs", 
            "tracking_summary": {
                "total": 0, 
                "recent": 0
            }, 
            "mimetype_inner": null, 
            "url_type": null, 
            "mimetype": null, 
            "cache_url": null, 
            "name": "j_lab_50_08", 
            "created": "2015-04-20T03:49:03.733167", 
            "url": "http://geoservices.rijkswaterstaat.nl/nis_kustlijnkaart", 
            "webstore_url": null, 
            "last_modified": null, 
            "position": 35, 
            "revision_id": "d5cbbaa4-d77c-4380-807f-783f6485c787", 
            "resource_type": null
        }, 
        {
            "resource_group_id": "5ad039bb-bd27-461f-8a39-154a31d0422a", 
            "protocol": "OGC:WMS", 
            "cache_last_updated": null, 
            "revision_timestamp": "2015-04-20T01:49:02.828340", 
            "webstore_last_updated": null, 
            "id": "acb8c461-dc1b-4447-a6e8-28dc1cc8ce28", 
            "size": null, 
            "state": "active", 
            "hash": "", 
            "description": "", 
            "format": "ogc:wms", 
            "tracking_summary": {
                "total": 0, 
                "recent": 0
            }, 
            "mimetype_inner": null, 
            "url_type": null, 
            "mimetype": null, 
            "cache_url": null, 
            "name": "j_lab_100_08", 
            "created": "2015-04-20T03:49:03.733173", 
            "url": "http://geoservices.rijkswaterstaat.nl/nis_kustlijnkaart", 
            "webstore_url": null, 
            "last_modified": null, 
            "position": 36, 
            "revision_id": "d5cbbaa4-d77c-4380-807f-783f6485c787", 
            "resource_type": null
        }, 
        {
            "resource_group_id": "5ad039bb-bd27-461f-8a39-154a31d0422a", 
            "protocol": "OGC:WFS", 
            "cache_last_updated": null, 
            "revision_timestamp": "2015-04-20T01:49:02.828340", 
            "webstore_last_updated": null, 
            "id": "0db66faa-b5c7-46e2-9e43-2cbf968b9101", 
            "size": null, 
            "state": "active", 
            "hash": "", 
            "description": "", 
            "format": "ogc:wfs", 
            "tracking_summary": {
                "total": 0, 
                "recent": 0
            }, 
            "mimetype_inner": null, 
            "url_type": null, 
            "mimetype": null, 
            "cache_url": null, 
            "name": "j_lab_100_08", 
            "created": "2015-04-20T03:49:03.733180", 
            "url": "http://geoservices.rijkswaterstaat.nl/nis_kustlijnkaart", 
            "webstore_url": null, 
            "last_modified": null, 
            "position": 37, 
            "revision_id": "d5cbbaa4-d77c-4380-807f-783f6485c787", 
            "resource_type": null
        }, 
        {
            "resource_group_id": "5ad039bb-bd27-461f-8a39-154a31d0422a", 
            "protocol": "OGC:WMS", 
            "cache_last_updated": null, 
            "revision_timestamp": "2015-04-20T01:49:02.828340", 
            "webstore_last_updated": null, 
            "id": "80959bcf-5463-4647-a58a-100b39502fae", 
            "size": null, 
            "state": "active", 
            "hash": "", 
            "description": "", 
            "format": "ogc:wms", 
            "tracking_summary": {
                "total": 0, 
                "recent": 0
            }, 
            "mimetype_inner": null, 
            "url_type": null, 
            "mimetype": null, 
            "cache_url": null, 
            "name": "j_raai_08", 
            "created": "2015-04-20T03:49:03.733186", 
            "url": "http://geoservices.rijkswaterstaat.nl/nis_kustlijnkaart", 
            "webstore_url": null, 
            "last_modified": null, 
            "position": 38, 
            "revision_id": "d5cbbaa4-d77c-4380-807f-783f6485c787", 
            "resource_type": null
        }, 
        {
            "resource_group_id": "5ad039bb-bd27-461f-8a39-154a31d0422a", 
            "protocol": "OGC:WFS", 
            "cache_last_updated": null, 
            "revision_timestamp": "2015-04-20T01:49:02.828340", 
            "webstore_last_updated": null, 
            "id": "08857173-b276-4acc-add7-40a6ca2e35d7", 
            "size": null, 
            "state": "active", 
            "hash": "", 
            "description": "", 
            "format": "ogc:wfs", 
            "tracking_summary": {
                "total": 0, 
                "recent": 0
            }, 
            "mimetype_inner": null, 
            "url_type": null, 
            "mimetype": null, 
            "cache_url": null, 
            "name": "j_raai_08", 
            "created": "2015-04-20T03:49:03.733192", 
            "url": "http://geoservices.rijkswaterstaat.nl/nis_kustlijnkaart", 
            "webstore_url": null, 
            "last_modified": null, 
            "position": 39, 
            "revision_id": "d5cbbaa4-d77c-4380-807f-783f6485c787", 
            "resource_type": null
        }, 
        {
            "resource_group_id": "5ad039bb-bd27-461f-8a39-154a31d0422a", 
            "protocol": "OGC:WMS", 
            "cache_last_updated": null, 
            "revision_timestamp": "2015-04-20T01:49:02.828340", 
            "webstore_last_updated": null, 
            "id": "fb5c6c0f-4f1f-4b04-ba7e-e22debbbef26", 
            "size": null, 
            "state": "active", 
            "hash": "", 
            "description": "", 
            "format": "ogc:wms", 
            "tracking_summary": {
                "total": 0, 
                "recent": 0
            }, 
            "mimetype_inner": null, 
            "url_type": null, 
            "mimetype": null, 
            "cache_url": null, 
            "name": "j_lab_25_07", 
            "created": "2015-04-20T03:49:03.733198", 
            "url": "http://geoservices.rijkswaterstaat.nl/nis_kustlijnkaart", 
            "webstore_url": null, 
            "last_modified": null, 
            "position": 40, 
            "revision_id": "d5cbbaa4-d77c-4380-807f-783f6485c787", 
            "resource_type": null
        }, 
        {
            "resource_group_id": "5ad039bb-bd27-461f-8a39-154a31d0422a", 
            "protocol": "OGC:WFS", 
            "cache_last_updated": null, 
            "revision_timestamp": "2015-04-20T01:49:02.828340", 
            "webstore_last_updated": null, 
            "id": "05a8f53d-24ca-4e35-9ea3-4904fc3f0017", 
            "size": null, 
            "state": "active", 
            "hash": "", 
            "description": "", 
            "format": "ogc:wfs", 
            "tracking_summary": {
                "total": 0, 
                "recent": 0
            }, 
            "mimetype_inner": null, 
            "url_type": null, 
            "mimetype": null, 
            "cache_url": null, 
            "name": "j_lab_25_07", 
            "created": "2015-04-20T03:49:03.733205", 
            "url": "http://geoservices.rijkswaterstaat.nl/nis_kustlijnkaart", 
            "webstore_url": null, 
            "last_modified": null, 
            "position": 41, 
            "revision_id": "d5cbbaa4-d77c-4380-807f-783f6485c787", 
            "resource_type": null
        }, 
        {
            "resource_group_id": "5ad039bb-bd27-461f-8a39-154a31d0422a", 
            "protocol": "OGC:WMS", 
            "cache_last_updated": null, 
            "revision_timestamp": "2015-04-20T01:49:02.828340", 
            "webstore_last_updated": null, 
            "id": "b6e86b93-dd1f-4738-9e30-912ecfaa50d9", 
            "size": null, 
            "state": "active", 
            "hash": "", 
            "description": "", 
            "format": "ogc:wms", 
            "tracking_summary": {
                "total": 0, 
                "recent": 0
            }, 
            "mimetype_inner": null, 
            "url_type": null, 
            "mimetype": null, 
            "cache_url": null, 
            "name": "j_lab_50_07", 
            "created": "2015-04-20T03:49:03.733211", 
            "url": "http://geoservices.rijkswaterstaat.nl/nis_kustlijnkaart", 
            "webstore_url": null, 
            "last_modified": null, 
            "position": 42, 
            "revision_id": "d5cbbaa4-d77c-4380-807f-783f6485c787", 
            "resource_type": null
        }, 
        {
            "resource_group_id": "5ad039bb-bd27-461f-8a39-154a31d0422a", 
            "protocol": "OGC:WFS", 
            "cache_last_updated": null, 
            "revision_timestamp": "2015-04-20T01:49:02.828340", 
            "webstore_last_updated": null, 
            "id": "41f4c4db-a9c5-499f-8d49-24b1b6b79e8e", 
            "size": null, 
            "state": "active", 
            "hash": "", 
            "description": "", 
            "format": "ogc:wfs", 
            "tracking_summary": {
                "total": 0, 
                "recent": 0
            }, 
            "mimetype_inner": null, 
            "url_type": null, 
            "mimetype": null, 
            "cache_url": null, 
            "name": "j_lab_50_07", 
            "created": "2015-04-20T03:49:03.733217", 
            "url": "http://geoservices.rijkswaterstaat.nl/nis_kustlijnkaart", 
            "webstore_url": null, 
            "last_modified": null, 
            "position": 43, 
            "revision_id": "d5cbbaa4-d77c-4380-807f-783f6485c787", 
            "resource_type": null
        }, 
        {
            "resource_group_id": "5ad039bb-bd27-461f-8a39-154a31d0422a", 
            "protocol": "OGC:WMS", 
            "cache_last_updated": null, 
            "revision_timestamp": "2015-04-20T01:49:02.828340", 
            "webstore_last_updated": null, 
            "id": "2caaf6ec-dbc7-47eb-aa3b-f170fdd71155", 
            "size": null, 
            "state": "active", 
            "hash": "", 
            "description": "", 
            "format": "ogc:wms", 
            "tracking_summary": {
                "total": 0, 
                "recent": 0
            }, 
            "mimetype_inner": null, 
            "url_type": null, 
            "mimetype": null, 
            "cache_url": null, 
            "name": "j_lab_100_07", 
            "created": "2015-04-20T03:49:03.733223", 
            "url": "http://geoservices.rijkswaterstaat.nl/nis_kustlijnkaart", 
            "webstore_url": null, 
            "last_modified": null, 
            "position": 44, 
            "revision_id": "d5cbbaa4-d77c-4380-807f-783f6485c787", 
            "resource_type": null
        }, 
        {
            "resource_group_id": "5ad039bb-bd27-461f-8a39-154a31d0422a", 
            "protocol": "OGC:WFS", 
            "cache_last_updated": null, 
            "revision_timestamp": "2015-04-20T01:49:02.828340", 
            "webstore_last_updated": null, 
            "id": "4bc08d4e-f867-44ca-a65e-bf9a3c682214", 
            "size": null, 
            "state": "active", 
            "hash": "", 
            "description": "", 
            "format": "ogc:wfs", 
            "tracking_summary": {
                "total": 0, 
                "recent": 0
            }, 
            "mimetype_inner": null, 
            "url_type": null, 
            "mimetype": null, 
            "cache_url": null, 
            "name": "j_lab_100_07", 
            "created": "2015-04-20T03:49:03.733229", 
            "url": "http://geoservices.rijkswaterstaat.nl/nis_kustlijnkaart", 
            "webstore_url": null, 
            "last_modified": null, 
            "position": 45, 
            "revision_id": "d5cbbaa4-d77c-4380-807f-783f6485c787", 
            "resource_type": null
        }, 
        {
            "resource_group_id": "5ad039bb-bd27-461f-8a39-154a31d0422a", 
            "protocol": "OGC:WMS", 
            "cache_last_updated": null, 
            "revision_timestamp": "2015-04-20T01:49:02.828340", 
            "webstore_last_updated": null, 
            "id": "0836273b-0c0f-4114-aeda-2295096b3062", 
            "size": null, 
            "state": "active", 
            "hash": "", 
            "description": "", 
            "format": "ogc:wms", 
            "tracking_summary": {
                "total": 0, 
                "recent": 0
            }, 
            "mimetype_inner": null, 
            "url_type": null, 
            "mimetype": null, 
            "cache_url": null, 
            "name": "j_raai_07", 
            "created": "2015-04-20T03:49:03.733236", 
            "url": "http://geoservices.rijkswaterstaat.nl/nis_kustlijnkaart", 
            "webstore_url": null, 
            "last_modified": null, 
            "position": 46, 
            "revision_id": "d5cbbaa4-d77c-4380-807f-783f6485c787", 
            "resource_type": null
        }, 
        {
            "resource_group_id": "5ad039bb-bd27-461f-8a39-154a31d0422a", 
            "protocol": "OGC:WFS", 
            "cache_last_updated": null, 
            "revision_timestamp": "2015-04-20T01:49:02.828340", 
            "webstore_last_updated": null, 
            "id": "31ef8e21-a51e-4654-a5a8-e0cd4b43b595", 
            "size": null, 
            "state": "active", 
            "hash": "", 
            "description": "", 
            "format": "ogc:wfs", 
            "tracking_summary": {
                "total": 0, 
                "recent": 0
            }, 
            "mimetype_inner": null, 
            "url_type": null, 
            "mimetype": null, 
            "cache_url": null, 
            "name": "j_raai_07", 
            "created": "2015-04-20T03:49:03.733242", 
            "url": "http://geoservices.rijkswaterstaat.nl/nis_kustlijnkaart", 
            "webstore_url": null, 
            "last_modified": null, 
            "position": 47, 
            "revision_id": "d5cbbaa4-d77c-4380-807f-783f6485c787", 
            "resource_type": null
        }, 
        {
            "resource_group_id": "5ad039bb-bd27-461f-8a39-154a31d0422a", 
            "protocol": "OGC:WMS", 
            "cache_last_updated": null, 
            "revision_timestamp": "2015-04-20T01:49:02.828340", 
            "webstore_last_updated": null, 
            "id": "fcd58ab5-b641-4cb5-a14d-c1a31d11295d", 
            "size": null, 
            "state": "active", 
            "hash": "", 
            "description": "", 
            "format": "ogc:wms", 
            "tracking_summary": {
                "total": 0, 
                "recent": 0
            }, 
            "mimetype_inner": null, 
            "url_type": null, 
            "mimetype": null, 
            "cache_url": null, 
            "name": "j_lab_25_06", 
            "created": "2015-04-20T03:49:03.733248", 
            "url": "http://geoservices.rijkswaterstaat.nl/nis_kustlijnkaart", 
            "webstore_url": null, 
            "last_modified": null, 
            "position": 48, 
            "revision_id": "d5cbbaa4-d77c-4380-807f-783f6485c787", 
            "resource_type": null
        }, 
        {
            "resource_group_id": "5ad039bb-bd27-461f-8a39-154a31d0422a", 
            "protocol": "OGC:WFS", 
            "cache_last_updated": null, 
            "revision_timestamp": "2015-04-20T01:49:02.828340", 
            "webstore_last_updated": null, 
            "id": "e269b0f8-61a1-4f07-af09-7792f64ed814", 
            "size": null, 
            "state": "active", 
            "hash": "", 
            "description": "", 
            "format": "ogc:wfs", 
            "tracking_summary": {
                "total": 0, 
                "recent": 0
            }, 
            "mimetype_inner": null, 
            "url_type": null, 
            "mimetype": null, 
            "cache_url": null, 
            "name": "j_lab_25_06", 
            "created": "2015-04-20T03:49:03.733254", 
            "url": "http://geoservices.rijkswaterstaat.nl/nis_kustlijnkaart", 
            "webstore_url": null, 
            "last_modified": null, 
            "position": 49, 
            "revision_id": "d5cbbaa4-d77c-4380-807f-783f6485c787", 
            "resource_type": null
        }, 
        {
            "resource_group_id": "5ad039bb-bd27-461f-8a39-154a31d0422a", 
            "protocol": "OGC:WMS", 
            "cache_last_updated": null, 
            "revision_timestamp": "2015-04-20T01:49:02.828340", 
            "webstore_last_updated": null, 
            "id": "2268d61f-e522-4c81-90af-78e437e067d1", 
            "size": null, 
            "state": "active", 
            "hash": "", 
            "description": "", 
            "format": "ogc:wms", 
            "tracking_summary": {
                "total": 0, 
                "recent": 0
            }, 
            "mimetype_inner": null, 
            "url_type": null, 
            "mimetype": null, 
            "cache_url": null, 
            "name": "j_lab_50_06", 
            "created": "2015-04-20T03:49:03.733261", 
            "url": "http://geoservices.rijkswaterstaat.nl/nis_kustlijnkaart", 
            "webstore_url": null, 
            "last_modified": null, 
            "position": 50, 
            "revision_id": "d5cbbaa4-d77c-4380-807f-783f6485c787", 
            "resource_type": null
        }, 
        {
            "resource_group_id": "5ad039bb-bd27-461f-8a39-154a31d0422a", 
            "protocol": "OGC:WFS", 
            "cache_last_updated": null, 
            "revision_timestamp": "2015-04-20T01:49:02.828340", 
            "webstore_last_updated": null, 
            "id": "59ec95ee-00b9-4752-af75-5209207dcfc0", 
            "size": null, 
            "state": "active", 
            "hash": "", 
            "description": "", 
            "format": "ogc:wfs", 
            "tracking_summary": {
                "total": 0, 
                "recent": 0
            }, 
            "mimetype_inner": null, 
            "url_type": null, 
            "mimetype": null, 
            "cache_url": null, 
            "name": "j_lab_50_06", 
            "created": "2015-04-20T03:49:03.733267", 
            "url": "http://geoservices.rijkswaterstaat.nl/nis_kustlijnkaart", 
            "webstore_url": null, 
            "last_modified": null, 
            "position": 51, 
            "revision_id": "d5cbbaa4-d77c-4380-807f-783f6485c787", 
            "resource_type": null
        }, 
        {
            "resource_group_id": "5ad039bb-bd27-461f-8a39-154a31d0422a", 
            "protocol": "OGC:WMS", 
            "cache_last_updated": null, 
            "revision_timestamp": "2015-04-20T01:49:02.828340", 
            "webstore_last_updated": null, 
            "id": "532fd45e-41fa-4f83-a8a5-0b45b9a4f4e8", 
            "size": null, 
            "state": "active", 
            "hash": "", 
            "description": "", 
            "format": "ogc:wms", 
            "tracking_summary": {
                "total": 0, 
                "recent": 0
            }, 
            "mimetype_inner": null, 
            "url_type": null, 
            "mimetype": null, 
            "cache_url": null, 
            "name": "j_lab_100_06", 
            "created": "2015-04-20T03:49:03.733274", 
            "url": "http://geoservices.rijkswaterstaat.nl/nis_kustlijnkaart", 
            "webstore_url": null, 
            "last_modified": null, 
            "position": 52, 
            "revision_id": "d5cbbaa4-d77c-4380-807f-783f6485c787", 
            "resource_type": null
        }, 
        {
            "resource_group_id": "5ad039bb-bd27-461f-8a39-154a31d0422a", 
            "protocol": "OGC:WFS", 
            "cache_last_updated": null, 
            "revision_timestamp": "2015-04-20T01:49:02.828340", 
            "webstore_last_updated": null, 
            "id": "7d4183e8-4efa-4eff-afbb-adffcf854308", 
            "size": null, 
            "state": "active", 
            "hash": "", 
            "description": "", 
            "format": "ogc:wfs", 
            "tracking_summary": {
                "total": 0, 
                "recent": 0
            }, 
            "mimetype_inner": null, 
            "url_type": null, 
            "mimetype": null, 
            "cache_url": null, 
            "name": "j_lab_100_06", 
            "created": "2015-04-20T03:49:03.733280", 
            "url": "http://geoservices.rijkswaterstaat.nl/nis_kustlijnkaart", 
            "webstore_url": null, 
            "last_modified": null, 
            "position": 53, 
            "revision_id": "d5cbbaa4-d77c-4380-807f-783f6485c787", 
            "resource_type": null
        }, 
        {
            "resource_group_id": "5ad039bb-bd27-461f-8a39-154a31d0422a", 
            "protocol": "OGC:WMS", 
            "cache_last_updated": null, 
            "revision_timestamp": "2015-04-20T01:49:02.828340", 
            "webstore_last_updated": null, 
            "id": "48cc6d55-c6f4-4759-9cdd-9882086deb66", 
            "size": null, 
            "state": "active", 
            "hash": "", 
            "description": "", 
            "format": "ogc:wms", 
            "tracking_summary": {
                "total": 0, 
                "recent": 0
            }, 
            "mimetype_inner": null, 
            "url_type": null, 
            "mimetype": null, 
            "cache_url": null, 
            "name": "j_raai_06", 
            "created": "2015-04-20T03:49:03.733286", 
            "url": "http://geoservices.rijkswaterstaat.nl/nis_kustlijnkaart", 
            "webstore_url": null, 
            "last_modified": null, 
            "position": 54, 
            "revision_id": "d5cbbaa4-d77c-4380-807f-783f6485c787", 
            "resource_type": null
        }, 
        {
            "resource_group_id": "5ad039bb-bd27-461f-8a39-154a31d0422a", 
            "protocol": "OGC:WFS", 
            "cache_last_updated": null, 
            "revision_timestamp": "2015-04-20T01:49:02.828340", 
            "webstore_last_updated": null, 
            "id": "93c90c10-2f9b-4a5c-b243-636b9491b613", 
            "size": null, 
            "state": "active", 
            "hash": "", 
            "description": "", 
            "format": "ogc:wfs", 
            "tracking_summary": {
                "total": 0, 
                "recent": 0
            }, 
            "mimetype_inner": null, 
            "url_type": null, 
            "mimetype": null, 
            "cache_url": null, 
            "name": "j_raai_06", 
            "created": "2015-04-20T03:49:03.733292", 
            "url": "http://geoservices.rijkswaterstaat.nl/nis_kustlijnkaart", 
            "webstore_url": null, 
            "last_modified": null, 
            "position": 55, 
            "revision_id": "d5cbbaa4-d77c-4380-807f-783f6485c787", 
            "resource_type": null
        }
    ], 
    "num_resources": 56, 
    "tags": [
        {
            "vocabulary_id": null, 
            "display_name": "Bescherming tegen water", 
            "name": "Bescherming tegen water", 
            "revision_timestamp": "2015-03-26T13:12:13.131839", 
            "state": "active", 
            "id": "4592f538-08f7-494a-a5b2-0fdae7f79ece"
        }, 
        {
            "vocabulary_id": null, 
            "display_name": "Kust en Zee", 
            "name": "Kust en Zee", 
            "revision_timestamp": "2015-03-26T13:12:13.131839", 
            "state": "active", 
            "id": "286fb772-897b-40cb-be20-6c3d9aac3ed8"
        }, 
        {
            "vocabulary_id": null, 
            "display_name": "NIS", 
            "name": "NIS", 
            "revision_timestamp": "2015-03-26T13:12:13.131839", 
            "state": "active", 
            "id": "dc0da510-ca5a-41ef-8f92-5fe97e212717"
        }, 
        {
            "vocabulary_id": null, 
            "display_name": "Veiligheid", 
            "name": "Veiligheid", 
            "revision_timestamp": "2015-03-26T13:12:13.131839", 
            "state": "active", 
            "id": "1f858f26-5eee-4710-8a1a-3ce49e3b4240"
        }
    ], 
    "theme_facet": "http://standaarden.overheid.nl/owms/terms/Bestuur", 
    "title": "Kustlijnkaarten: Ligging JARKUS-raaien langs de Nederlandse Kust (2006 t/m 2012)", 
    "maintainer_displayname": "Ministerie van Infrastructuur en Milieu | Rijkswaterstaat", 
    "theme_displayname": "Bestuur | Organisatie en beleid", 
    "temporal_from": "1998-01-01", 
    "tracking_summary": {
        "total": 0, 
        "recent": 0
    }, 
    "groups": [], 
    "creator_user_id": "53359fa1-154d-4d03-8408-3582c9e0dcbc", 
    "relationships_as_subject": [], 
    "revision_timestamp": "2015-03-26T13:12:13.131839", 
    "identifier": "730bc0c4-638d-4cd2-a44d-38b6e28ecff5", 
    "name": "kustlijnkaarten-ligging-jarkus-raaien-langs-de-nederlandse-kust-2006-t-m-2012", 
    "language": "nl-NL", 
    "temporal_to": "2012-12-31", 
    "accrual_periodicity": "http://purl.org/cld/freq/irregular", 
    "notes": "Ligging van de JARKUS-raaien langs de nederlandse Kust. In het kader van het JARKUS programma worden jaarlijks langs de jarjusraaien hoogte en dieptemetingen verricht. Deze metingen dienen als input voor onder andere onderzoek en toetsing basiskustlijnpositie. Het JARKUS-bestand is in beheer bij de Waterdienst. Deze laag wordt gebruikt voor weergave in de Kustlijnkaartenboeken.", 
    "license_title": "CC-0", 
    "modified": "1997-01-01", 
    "url": null, 
    "extras": [
        {
            "value": "http://standaarden.overheid.nl/owms/terms/Organisatie_en_beleid", 
            "key": "subtheme_facet"
        }
    ], 
    "license_url": "http://creativecommons.org/publicdomain/zero/1.0/deed.nl", 
    "organization": {
        "description": "", 
        "title": "Nationaal Georegister", 
        "created": "2015-03-26T12:56:19.147623", 
        "approval_status": "approved", 
        "revision_timestamp": "2015-03-26T11:56:19.121612", 
        "is_organization": true, 
        "state": "active", 
        "image_url": "20150326-115619.119226ngr.png", 
        "revision_id": "918c4dfd-7496-4ac4-8b0d-a95fe2682aa9", 
        "type": "organization", 
        "id": "a9a8e392-9f69-493e-8b44-4a1586725a66", 
        "name": "nationaal-georegister"
    }, 
    "revision_id": "2e60b10c-da07-4a30-b96d-030b6220a48a", 
    "landingpage": ""
}