{
    "owner_org": "a9a8e392-9f69-493e-8b44-4a1586725a66", 
    "maintainer": "http://standaarden.overheid.nl/owms/terms/Limburg", 
    "relationships_as_object": [], 
    "lod_stars": "0", 
    "private": false, 
    "maintainer_email": "hf.groen@prvlimburg.nl", 
    "num_tags": 5, 
    "id": "04dc0fef-2526-454f-8ec5-90ffaaad5601", 
    "metadata_created": "2015-04-18T01:54:15.230075", 
    "metadata_modified": "2015-04-20T01:44:31.815860", 
    "author": null, 
    "author_email": null, 
    "isopen": true, 
    "state": "active", 
    "source": "ngr", 
    "theme": "planningCadastre", 
    "version": null, 
    "maintainer_facet": "http://standaarden.overheid.nl/owms/terms/Limburg", 
    "md_soortwijziging": ":updated", 
    "spatial": "Limburg", 
    "license_id": "publiek-domein", 
    "contact_point": "ngr@test.com", 
    "type": "dataset", 
    "md_uri": "http://nationaalgeoregister.nl/geonetwork?uuid=f402a680-4085-48bb-b575-2b440afccecd", 
    "resources": [
        {
            "resource_group_id": "0cd1470e-bc89-4d5d-8887-4071269fe3a8", 
            "protocol": "OGC:WMS", 
            "cache_last_updated": null, 
            "revision_timestamp": "2015-04-20T01:44:31.814915", 
            "webstore_last_updated": null, 
            "id": "a7608186-f711-45ee-a460-e30038d3f734", 
            "size": null, 
            "state": "active", 
            "hash": "", 
            "description": "", 
            "format": "ogc:wms", 
            "tracking_summary": {
                "total": 0, 
                "recent": 0
            }, 
            "mimetype_inner": null, 
            "url_type": null, 
            "mimetype": null, 
            "cache_url": null, 
            "name": "polact_p4_v", 
            "created": "2015-04-20T03:44:31.856287", 
            "url": "http://portal.prvlimburg.nl/geoservices/polact_1_perspectieven?", 
            "webstore_url": null, 
            "last_modified": null, 
            "position": 0, 
            "revision_id": "2f9406f2-4f22-47f9-a4ac-457712bcfe2b", 
            "resource_type": null
        }, 
        {
            "resource_group_id": "0cd1470e-bc89-4d5d-8887-4071269fe3a8", 
            "protocol": "OGC:WFS", 
            "cache_last_updated": null, 
            "revision_timestamp": "2015-04-20T01:44:31.814915", 
            "webstore_last_updated": null, 
            "id": "e106c313-9a04-4fb4-ab6d-db3eb4bde35d", 
            "size": null, 
            "state": "active", 
            "hash": "", 
            "description": "", 
            "format": "ogc:wfs", 
            "tracking_summary": {
                "total": 0, 
                "recent": 0
            }, 
            "mimetype_inner": null, 
            "url_type": null, 
            "mimetype": null, 
            "cache_url": null, 
            "name": "polact_p4_v", 
            "created": "2015-04-20T03:44:31.856316", 
            "url": "http://portal.prvlimburg.nl/geoservices/polact_1_perspectieven?", 
            "webstore_url": null, 
            "last_modified": null, 
            "position": 1, 
            "revision_id": "2f9406f2-4f22-47f9-a4ac-457712bcfe2b", 
            "resource_type": null
        }
    ], 
    "num_resources": 2, 
    "tags": [
        {
            "vocabulary_id": null, 
            "display_name": "beleid", 
            "name": "beleid", 
            "revision_timestamp": "2015-04-18T01:54:15.230075", 
            "state": "active", 
            "id": "87984616-7413-4c79-b4b4-e7a81141668e"
        }, 
        {
            "vocabulary_id": null, 
            "display_name": "landbouw", 
            "name": "landbouw", 
            "revision_timestamp": "2015-04-18T01:54:15.230075", 
            "state": "active", 
            "id": "bb13106d-9cdf-44d5-877a-e7242c1358f5"
        }, 
        {
            "vocabulary_id": null, 
            "display_name": "landbouwgronden", 
            "name": "landbouwgronden", 
            "revision_timestamp": "2015-04-18T01:54:15.230075", 
            "state": "active", 
            "id": "8eec6081-852e-4c94-9ce1-8e60cbfab244"
        }, 
        {
            "vocabulary_id": null, 
            "display_name": "landelijke gebieden", 
            "name": "landelijke gebieden", 
            "revision_timestamp": "2015-04-18T01:54:15.230075", 
            "state": "active", 
            "id": "3a0c8c90-7eb1-4792-92c3-2671e727caa6"
        }, 
        {
            "vocabulary_id": null, 
            "display_name": "structuurplannen", 
            "name": "structuurplannen", 
            "revision_timestamp": "2015-04-18T01:54:15.230075", 
            "state": "active", 
            "id": "d1ada1f5-5a9f-41c4-90f9-afa88fa9fc53"
        }
    ], 
    "title": "Perspectief 4 Vitaal landelijk gebied", 
    "maintainer_displayname": "Provincie | Limburg", 
    "temporal_from": "2012-11-30", 
    "tracking_summary": {
        "total": 0, 
        "recent": 0
    }, 
    "groups": [], 
    "creator_user_id": "53359fa1-154d-4d03-8408-3582c9e0dcbc", 
    "relationships_as_subject": [], 
    "revision_timestamp": "2015-04-18T01:54:15.230075", 
    "identifier": "f402a680-4085-48bb-b575-2b440afccecd", 
    "name": "perspectief-4-vitaal-landelijk-gebied", 
    "language": "nl-NL", 
    "url": null, 
    "notes": "Perspectief 4 heeft betrekking op overwegend landbouwgebieden met een van gebied tot gebied verschillende aard en dichtheid aan landschappelijke en cultuurhistorische kwaliteiten. In Noord- en Midden Limburg valt het perspectief vrijwel overal samen met verwevingsgebied intensieve veehouderij (zie POL-aanvulling Reconstructieplan). Daarnaast komen op kleinere schaal woonbebouwing, al dan niet solitaire bedrijfsgebouwen, toeristisch-recreatieve voorzieningen en infrastructuur voor.\nSoms gaat het om oud-bouwlanden waarbij een gaaf cultuurhistorisch kavel-, wegen- en bebouwingspatroon samengaat met monumentale bebouwing en/of met landschappelijke openheid Andere kwaliteiten die voor kunnen komen zijn stiltegebied, grondwaterbeschermingsgebied, landschappelijke openheid of een bebouwingsarm karakter, leefgebieden voor ganzen en weidevogels. De gebiedsafbakening van P4 is indicatief.", 
    "license_title": "Publiek Domein", 
    "modified": "2012-11-30", 
    "license_url": "http://creativecommons.org/publicdomain/mark/1.0/deed.nl", 
    "organization": {
        "description": "", 
        "title": "Nationaal Georegister", 
        "created": "2015-03-26T12:56:19.147623", 
        "approval_status": "approved", 
        "revision_timestamp": "2015-03-26T11:56:19.121612", 
        "is_organization": true, 
        "state": "active", 
        "image_url": "20150326-115619.119226ngr.png", 
        "revision_id": "918c4dfd-7496-4ac4-8b0d-a95fe2682aa9", 
        "type": "organization", 
        "id": "a9a8e392-9f69-493e-8b44-4a1586725a66", 
        "name": "nationaal-georegister"
    }, 
    "revision_id": "aa34ce90-0c6c-4aa7-9fb0-cf09ea7dc51c", 
    "landingpage": ""
}